BMI_heum/BMI_module.py
BMI_heum-0.0.0.1.dist-info/METADATA
BMI_heum-0.0.0.1.dist-info/WHEEL
BMI_heum-0.0.0.1.dist-info/top_level.txt
BMI_heum-0.0.0.1.dist-info/RECORD
