Metadata-Version: 2.1
Name: BMI-heum
Version: 0.0.0.1
Summary: measurement_BMI Test version
Home-page: https://lingua.blog.me/...
Author: MinHeum Lee
Author-email: alsgma112@naver.com
License: MIT
Platform: UNKNOWN
Requires-Python: >=3
